dftracer/bin/dftracer_event_count
dftracer/bin/dftracer_info
dftracer/bin/dftracer_merge
dftracer/bin/dftracer_pgzip
dftracer/bin/dftracer_reader
dftracer/bin/dftracer_split
dftracer/bin/dftracer_tar
dftracer/include/xxhash.h
dftracer/include/yyjson.h
dftracer/include/cpp-logger/clogger.h
dftracer/include/cpp-logger/cpp_logger_config.hpp
dftracer/include/cpp-logger/logger.h
dftracer/include/dftracer/utils/common/archive_format.h
dftracer/include/dftracer/utils/common/config.h
dftracer/include/dftracer/utils/common/constants.h
dftracer/include/dftracer/utils/common/platform_compat.h
dftracer/include/dftracer/utils/common/typedefs.h
dftracer/include/dftracer/utils/indexer/checkpoint.h
dftracer/include/dftracer/utils/indexer/error.h
dftracer/include/dftracer/utils/indexer/gzip_indexer.h
dftracer/include/dftracer/utils/indexer/indexer.h
dftracer/include/dftracer/utils/indexer/indexer_factory.h
dftracer/include/dftracer/utils/indexer/tar_indexer.h
dftracer/include/dftracer/utils/pipeline/error.h
dftracer/include/dftracer/utils/pipeline/pipeline.h
dftracer/include/dftracer/utils/pipeline/pipeline_output.h
dftracer/include/dftracer/utils/pipeline/executors/executor.h
dftracer/include/dftracer/utils/pipeline/executors/executor_context.h
dftracer/include/dftracer/utils/pipeline/executors/executor_factory.h
dftracer/include/dftracer/utils/pipeline/executors/executor_task_output.h
dftracer/include/dftracer/utils/pipeline/executors/executor_type.h
dftracer/include/dftracer/utils/pipeline/executors/progress_callback.h
dftracer/include/dftracer/utils/pipeline/tasks/function_task.h
dftracer/include/dftracer/utils/pipeline/tasks/task.h
dftracer/include/dftracer/utils/pipeline/tasks/task_context.h
dftracer/include/dftracer/utils/pipeline/tasks/task_result.h
dftracer/include/dftracer/utils/pipeline/tasks/task_tag.h
dftracer/include/dftracer/utils/pipeline/tasks/typed_task.h
dftracer/include/dftracer/utils/reader/error.h
dftracer_utils-0.0.4.dist-info/METADATA
dftracer_utils-0.0.4.dist-info/WHEEL
dftracer_utils-0.0.4.dist-info/RECORD
dftracer_utils-0.0.4.dist-info/licenses/LICENSE
